tian_driver/__init__.py
tian_driver/driver.py
tian_driver/file.py
tian_driver/mem.py
tian_driver/migration.py
tian_driver/mock.py
tian_driver/mongo.py
tian_driver/postgres.py
tian_driver/redis.py
tian_driver/sheet.py
tian_driver/sql_alchemy.py
tian_driver/sqllite.py
tian_drive-0.1.0.dist-info/LICENSE
tian_drive-0.1.0.dist-info/METADATA
tian_drive-0.1.0.dist-info/WHEEL
tian_drive-0.1.0.dist-info/RECORD
